{"data":[{"id":"ra1l0yelz6b4Jz5WL5d6","label":"Super Organization Administrator","type":"SUPER_ADMIN","status":"ACTIVE","created":"2021-04-14T08:03:55.000Z","lastUpdated":"2021-04-14T08:03:55.000Z","assignmentType":"USER","_links":{"assignee":{"href":"https://lyvoc-migration-a.okta.com/api/v1/users/00ul0yelxDhmIjTBF5d6"}}},{"id":"ra1l6wkdauxdnLnqw5d6","label":"Super Organization Administrator","type":"SUPER_ADMIN","status":"ACTIVE","created":"2021-04-15T09:19:25.000Z","lastUpdated":"2021-04-15T09:19:25.000Z","assignmentType":"USER","_links":{"assignee":{"href":"https://lyvoc-migration-a.okta.com/api/v1/users/00ul6vw4mL8fVqGM15d6"}}},{"id":"gramwrkm0oj1P2UuX5d6","label":"Super Organization Administrator","type":"SUPER_ADMIN","status":"ACTIVE","created":"2021-04-23T08:56:21.000Z","lastUpdated":"2021-04-23T08:56:21.000Z","assignmentType":"GROUP","_links":{"assignee":{"href":"https://lyvoc-migration-a.okta.com/api/v1/groups/00gl6yt3uAZ2MDLPF5d6"}}},{"id":"ra1lartibnwItfWn15d6","label":"Super Organization Administrator","type":"SUPER_ADMIN","status":"ACTIVE","created":"2021-04-16T08:47:16.000Z","lastUpdated":"2021-04-16T08:47:16.000Z","assignmentType":"USER","_links":{"assignee":{"href":"https://lyvoc-migration-a.okta.com/api/v1/users/00ulash9iSOMeGbZB5d6"}}}]}